{
    "id": "64326b65-73e4-4385-ab79-916eff944a51",
    "joints": [
        {
            "id": "j0",
            "x": 9,
            "y": 18
        },
        {
            "id": "j1",
            "x": 15,
            "y": 16
        },
        {
            "id": "j2",
            "x": 9,
            "y": 15
        },
        {
            "id": "j3",
            "x": 18,
            "y": 11
        },
        {
            "id": "j4",
            "x": 17,
            "y": 14
        },
        {
            "id": "j5",
            "x": 20,
            "y": 18
        }
    ],
    "bones": [
        {
            "id": "b0",
            "joint1_id": "j0",
            "joint2_id": "j1"
        },
        {
            "id": "b1",
            "joint1_id": "j1",
            "joint2_id": "j2"
        },
        {
            "id": "b2",
            "joint1_id": "j2",
            "joint2_id": "j3"
        },
        {
            "id": "b3",
            "joint1_id": "j3",
            "joint2_id": "j4"
        },
        {
            "id": "b4",
            "joint1_id": "j4",
            "joint2_id": "j5"
        }
    ],
    "muscles": [
        {
            "id": "m0",
            "bone1_id": "b3",
            "bone2_id": "b4"
        },
        {
            "id": "m1",
            "bone1_id": "b2",
            "bone2_id": "b3"
        },
        {
            "id": "m2",
            "bone1_id": "b1",
            "bone2_id": "b2"
        },
        {
            "id": "m3",
            "bone1_id": "b0",
            "bone2_id": "b1"
        }
    ]
}